splunk_appinspect/README.md
splunk_appinspect/__init__.py
splunk_appinspect/alert_actions.py
splunk_appinspect/alert_actions_configuration_file.py
splunk_appinspect/app.py
splunk_appinspect/app_configuration_file.py
splunk_appinspect/app_package_handler.py
splunk_appinspect/app_util.py
splunk_appinspect/authentication_configuration_file.py
splunk_appinspect/authorize_configuration_file.py
splunk_appinspect/canary_modules.py
splunk_appinspect/check_messages.py
splunk_appinspect/checks.py
splunk_appinspect/collections_configuration_file.py
splunk_appinspect/command_line_helpers.py
splunk_appinspect/configuration_file.py
splunk_appinspect/configuration_parser.py
splunk_appinspect/constants.py
splunk_appinspect/cron_expression.py
splunk_appinspect/custom_commands.py
splunk_appinspect/custom_types.py
splunk_appinspect/custom_visualizations.py
splunk_appinspect/decorators.py
splunk_appinspect/environment_validator.py
splunk_appinspect/feedback_file_generator.py
splunk_appinspect/file_resource.py
splunk_appinspect/file_view.py
splunk_appinspect/indexes_configuration_file.py
splunk_appinspect/inputs_configuration_file.py
splunk_appinspect/inputs_specification_file.py
splunk_appinspect/inspected_file.py
splunk_appinspect/iter_ext.py
splunk_appinspect/lookup.py
splunk_appinspect/main.py
splunk_appinspect/modular_inputs.py
splunk_appinspect/mutually_exclusive_option.py
splunk_appinspect/outputs_configuration_file.py
splunk_appinspect/props_configuration_file.py
splunk_appinspect/regex_matcher.py
splunk_appinspect/reporter.py
splunk_appinspect/resource_manager.py
splunk_appinspect/rest_map.py
splunk_appinspect/rest_map_configuration_file.py
splunk_appinspect/saved_searches.py
splunk_appinspect/saved_searches_configuration_file.py
splunk_appinspect/sideview_utils_modules.py
splunk_appinspect/splunk_default_source_type_list.py
splunk_appinspect/splunk_defined_authorize_capability_list.py
splunk_appinspect/splunk_defined_conf_file_list.py
splunk_appinspect-4.1.2.dist-info/METADATA
splunk_appinspect-4.1.2.dist-info/WHEEL
splunk_appinspect-4.1.2.dist-info/entry_points.txt
splunk_appinspect-4.1.2.dist-info/licenses/LICENSE
splunk_appinspect-4.1.2.dist-info/RECORD
